youarehere/__init__.py
youarehere-1.0.1.dist-info/entry_points.txt
youarehere-1.0.1.dist-info/LICENSE
youarehere-1.0.1.dist-info/WHEEL
youarehere-1.0.1.dist-info/METADATA
youarehere-1.0.1.dist-info/RECORD
