Metadata-Version: 2.1
Name: youarehere
Version: 1.0.1
Summary: Route53 DNS utility
Home-page: https://github.com/j6k4m8/youarehere
License: Apache-2.0
Author: Jordan Matelsky
Author-email: j6k4m8@gmail.com
Requires-Python: >=3.6,<4.0
Classifier: License :: OSI Approved :: Apache Software License
Classifier: Programming Language :: Python :: 3
Classifier: Programming Language :: Python :: 3.10
Classifier: Programming Language :: Python :: 3.6
Classifier: Programming Language :: Python :: 3.7
Classifier: Programming Language :: Python :: 3.8
Classifier: Programming Language :: Python :: 3.9
Requires-Dist: boto3 (>=1.10.43,<2.0.0)
Requires-Dist: click (>=7.0,<8.0)
Requires-Dist: requests (>=2.22.0,<3.0.0)
